sentinel.py
sentinel-0.2.0.dist-info/LICENSE
sentinel-0.2.0.dist-info/WHEEL
sentinel-0.2.0.dist-info/METADATA
sentinel-0.2.0.dist-info/RECORD
