Metadata-Version: 2.1
Name: sentinel
Version: 0.2.0
Summary: Create sentinel objects, akin to None, NotImplemented, Ellipsis
Home-page: https://github.com/eddieantonio/sentinel
License: MIT
Author: Eddie Antonio Santos
Author-email: easantos@ualberta.ca
Requires-Python: >=3.6,<4.0
Classifier: Development Status :: 4 - Beta
Classifier: Intended Audience :: Developers
Classifier: License :: OSI Approved :: MIT License
Classifier: Operating System :: OS Independent
Classifier: Programming Language :: Python :: 3
Classifier: Programming Language :: Python :: 3.6
Classifier: Programming Language :: Python :: 3.7
Classifier: Programming Language :: Python :: 3.8
Classifier: Programming Language :: Python :: 3.9
Classifier: Topic :: Software Development :: Libraries :: Python Modules
Project-URL: Repository, https://github.com/eddieantonio/sentinel.git
